mastermindc/__init__.py
mastermindc/mastermindc.py
mastermindc-1.0.1.dist-info/DESCRIPTION.rst
mastermindc-1.0.1.dist-info/METADATA
mastermindc-1.0.1.dist-info/RECORD
mastermindc-1.0.1.dist-info/WHEEL
mastermindc-1.0.1.dist-info/entry_points.txt
mastermindc-1.0.1.dist-info/metadata.json
mastermindc-1.0.1.dist-info/top_level.txt
