Metadata-Version: 2.0
Name: mastermindc
Version: 1.0.1
Summary: A mastermind playing computer
Home-page: UNKNOWN
Author: Alek Westover
Author-email: alek.westover@gmail.com
License: UNKNOWN
Keywords: test mastermind
Platform: UNKNOWN
